fio_taxa/__init__.py
fio_taxa/scripts/__init__.py
fio_taxa/scripts/cli.py
fio_taxa-1.0.0.dist-info/top_level.txt
fio_taxa-1.0.0.dist-info/entry_points.txt
fio_taxa-1.0.0.dist-info/METADATA
fio_taxa-1.0.0.dist-info/DESCRIPTION.rst
fio_taxa-1.0.0.dist-info/metadata.json
fio_taxa-1.0.0.dist-info/WHEEL
fio_taxa-1.0.0.dist-info/RECORD
