Metadata-Version: 2.0
Name: fio-taxa
Version: 1.0.0
Summary: Classification of GeoJSON features
Home-page: https://github.com/sgillies/fio_taxa
Author: Sean Gillies
Author-email: sean.gillies@gmail.com
License: MIT
Platform: UNKNOWN
Requires-Dist: click
Requires-Dist: fiona
Provides-Extra: test
Requires-Dist: pytest; extra == 'test'
